autograder/__init__.py
autograder/__main__.py
autograder/autograder.py
autograder/config_manager.py
autograder/default_config.toml
autograder/default_stdout_formatters.py
autograder/guide.py
autograder/output_summary.py
autograder/plagiarism_detection/__init__.py
autograder/plagiarism_detection/comparison.py
autograder/plagiarism_detection/lexers/CLexer.py
autograder/plagiarism_detection/lexers/CppLexer.py
autograder/plagiarism_detection/lexers/Java8Lexer.py
autograder/plagiarism_detection/lexers/Python3Lexer.py
autograder/plagiarism_detection/lexers/Python3Parser.py
autograder/plagiarism_detection/plagiarism_detection.py
autograder/testcase_types/cpython/helpers/test_helper.py
autograder/testcase_types/cpython/python.py
autograder/testcase_types/cpython/templates/sample_student_submission.py
autograder/testcase_types/cpython/templates/tests/output/testcase_template2.txt
autograder/testcase_types/cpython/templates/tests/testcases/testcase_template1.py
autograder/testcase_types/cpython/templates/tests/testcases/testcase_template2.py
autograder/testcase_types/gcc/c++_templates/sample_student_submission.cpp
autograder/testcase_types/gcc/c++_templates/tests/output/testcase_template2.txt
autograder/testcase_types/gcc/c++_templates/tests/testcases/testcase_template1.cpp
autograder/testcase_types/gcc/c++_templates/tests/testcases/testcase_template2.cpp
autograder/testcase_types/gcc/c.py
autograder/testcase_types/gcc/c_templates/sample_student_submission.c
autograder/testcase_types/gcc/c_templates/tests/output/testcase_template2.txt
autograder/testcase_types/gcc/c_templates/tests/testcases/testcase_template1.c
autograder/testcase_types/gcc/c_templates/tests/testcases/testcase_template2.c
autograder/testcase_types/gcc/cpp.py
autograder/testcase_types/gcc/helpers/test_helper.c
autograder/testcase_types/gcc/memleak/memleak_detector.c
autograder/testcase_types/gcc/memleak/memleak_detector.h
autograder/testcase_types/javac/extra/jna.jar
assignment_autograder-3.7.6.dist-info/entry_points.txt
assignment_autograder-3.7.6.dist-info/LICENSE
assignment_autograder-3.7.6.dist-info/WHEEL
assignment_autograder-3.7.6.dist-info/METADATA
assignment_autograder-3.7.6.dist-info/RECORD
